latest_pypi_version/__init__.py
latest_pypi_version/cli.py
latest_pypi_version-1.0.0.dist-info/METADATA
latest_pypi_version-1.0.0.dist-info/WHEEL
latest_pypi_version-1.0.0.dist-info/entry_points.txt
latest_pypi_version-1.0.0.dist-info/RECORD
