Metadata-Version: 2.3
Name: latest-pypi-version
Version: 1.0.0
Summary: CLI tool to check the latest version of a PyPI package
Author: Roman Zydyk
Author-email: roman.zydyk@quantlane.com
Requires-Python: >=3.12
Classifier: Programming Language :: Python :: 3
Classifier: Programming Language :: Python :: 3.12
Classifier: Programming Language :: Python :: 3.13
Requires-Dist: requests (>=2.32.3,<3.0.0)
Requires-Dist: rich (>=13.9.4,<14.0.0)
Requires-Dist: typer (>=0.15.2,<0.16.0)
